dyspyosis/__init__.py
dyspyosis/autoencoder.py
dyspyosis/dyspyosis.py
dyspyosis/utils.py
dyspyosis-0.0.2.dist-info/LICENSE
dyspyosis-0.0.2.dist-info/METADATA
dyspyosis-0.0.2.dist-info/WHEEL
dyspyosis-0.0.2.dist-info/top_level.txt
dyspyosis-0.0.2.dist-info/RECORD
