Metadata-Version: 2.1
Name: dyspyosis
Version: 0.0.2
Summary: Calculate dysbiosis scores using Python
Home-page: https://github.com/raeslab/dyspyosis/
Author: Sebastian Proost
Author-email: sebastian.proost@gmail.com
License: Creative Commons Attribution-NonCommercial-ShareAlike 4.0. https://creativecommons.org/licenses/by-nc-sa/4.0/
Project-URL: Bug Tracker, https://github.com/raeslab/dyspyosis/issues
Classifier: Programming Language :: Python :: 3
Classifier: Operating System :: OS Independent
Requires-Python: >=3.10
License-File: LICENSE
Requires-Dist: numpy >=1.26.3
Requires-Dist: pandas >=2.1.4
Requires-Dist: scikit-learn >=1.3.2
Requires-Dist: tensorflow ==2.10.1
Requires-Dist: keras ==2.10.0
